<TextureAtlas imagePath="Untitled-1.png">
	<SubTexture name="00.png" x="0" y="0" w="320" h="240"/>
	<SubTexture name="01.png" x="320" y="0" w="320" h="240"/>
	<SubTexture name="02.png" x="640" y="0" w="320" h="240"/>
	<SubTexture name="03.png" x="960" y="0" w="320" h="240"/>
	<SubTexture name="04.png" x="1280" y="0" w="320" h="240"/>
	<SubTexture name="05.png" x="1600" y="0" w="320" h="240"/>
	<SubTexture name="06.png" x="0" y="240" w="320" h="240"/>
	<SubTexture name="07.png" x="320" y="240" w="320" h="240"/>
	<SubTexture name="08.png" x="640" y="240" w="320" h="240"/>
	<SubTexture name="09.png" x="960" y="240" w="320" h="240"/>
	<SubTexture name="10.png" x="1280" y="240" w="320" h="240"/>
	<SubTexture name="11.png" x="1600" y="240" w="320" h="240"/>
	<SubTexture name="12.png" x="0" y="480" w="320" h="240"/>
	<SubTexture name="13.png" x="320" y="480" w="320" h="240"/>
	<SubTexture name="14.png" x="640" y="480" w="320" h="240"/>
	<SubTexture name="15.png" x="960" y="480" w="320" h="240"/>
	<SubTexture name="16.png" x="1280" y="480" w="320" h="240"/>
	<SubTexture name="17.png" x="1600" y="480" w="320" h="240"/>
	<SubTexture name="18.png" x="0" y="720" w="320" h="240"/>
	<SubTexture name="19.png" x="320" y="720" w="320" h="240"/>
	<SubTexture name="20.png" x="640" y="720" w="320" h="240"/>
	<SubTexture name="21.png" x="960" y="720" w="320" h="240"/>
	<SubTexture name="22.png" x="1280" y="720" w="320" h="240"/>
	<SubTexture name="23.png" x="1600" y="720" w="320" h="240"/>
	<SubTexture name="24.png" x="0" y="960" w="320" h="240"/>
	<SubTexture name="25.png" x="320" y="960" w="320" h="240"/>
	<SubTexture name="26.png" x="640" y="960" w="320" h="240"/>
	<SubTexture name="27.png" x="960" y="960" w="320" h="240"/>
	<SubTexture name="28.png" x="1280" y="960" w="320" h="240"/>
	<SubTexture name="29.png" x="1600" y="960" w="320" h="240"/>
</TextureAtlas>
